README.md
setup.cfg
setup.py
kaelib/__init__.py
kaelib/api.py
kaelib/spec.py
kaelib.egg-info/PKG-INFO
kaelib.egg-info/SOURCES.txt
kaelib.egg-info/dependency_links.txt
kaelib.egg-info/requires.txt
kaelib.egg-info/top_level.txt