Metadata-Version: 2.1
Name: kaelib
Version: 0.0.10
Summary: kae api library
Home-page: https://github.com/kaecloud/kaelib
Author: Yu Yang
Author-email: yangyu@geetest.com
License: UNKNOWN
Platform: UNKNOWN
